griffe2md-1.2.6.dist-info/METADATA
griffe2md-1.2.6.dist-info/WHEEL
griffe2md-1.2.6.dist-info/entry_points.txt
griffe2md-1.2.6.dist-info/licenses/LICENSE
griffe2md/__init__.py
griffe2md/_internal/__init__.py
griffe2md/_internal/cli.py
griffe2md/_internal/config.py
griffe2md/_internal/debug.py
griffe2md/_internal/main.py
griffe2md/_internal/rendering.py
griffe2md/cli.py
griffe2md/main.py
griffe2md/rendering.py
griffe2md/templates/attribute.md.jinja
griffe2md/templates/children.md.jinja
griffe2md/templates/class.md.jinja
griffe2md/templates/docstring.md.jinja
griffe2md/templates/docstring/admonition.md.jinja
griffe2md/templates/docstring/attributes.md.jinja
griffe2md/templates/docstring/classes.md.jinja
griffe2md/templates/docstring/examples.md.jinja
griffe2md/templates/docstring/functions.md.jinja
griffe2md/templates/docstring/modules.md.jinja
griffe2md/templates/docstring/other_parameters.md.jinja
griffe2md/templates/docstring/parameters.md.jinja
griffe2md/templates/docstring/raises.md.jinja
griffe2md/templates/docstring/receives.md.jinja
griffe2md/templates/docstring/returns.md.jinja
griffe2md/templates/docstring/warns.md.jinja
griffe2md/templates/docstring/yields.md.jinja
griffe2md/templates/expression.md.jinja
griffe2md/templates/function.md.jinja
griffe2md/templates/module.md.jinja
griffe2md/templates/signature.md.jinja
griffe2md/templates/summary.md.jinja
griffe2md/templates/summary/attributes.md.jinja
griffe2md/templates/summary/classes.md.jinja
griffe2md/templates/summary/functions.md.jinja
griffe2md/templates/summary/modules.md.jinja
griffe2md-1.2.6.dist-info/RECORD
