Metadata-Version: 2.4
Name: griffe2md
Version: 1.2.6
Summary: Output API docs to Markdown using Griffe.
Author-Email: =?utf-8?q?Timoth=C3=A9e_Mazzucotelli?= <dev@pawamoy.fr>
License-Expression: ISC
License-File: LICENSE
Classifier: Development Status :: 4 - Beta
Classifier: Intended Audience :: Developers
Classifier: Programming Language :: Python
Classifier: Programming Language :: Python :: 3
Classifier: Programming Language :: Python :: 3 :: Only
Classifier: Programming Language :: Python :: 3.10
Classifier: Programming Language :: Python :: 3.11
Classifier: Programming Language :: Python :: 3.12
Classifier: Programming Language :: Python :: 3.13
Classifier: Programming Language :: Python :: 3.14
Classifier: Topic :: Documentation
Classifier: Topic :: Software Development
Classifier: Topic :: Utilities
Classifier: Typing :: Typed
Project-URL: Homepage, https://mkdocstrings.github.io/griffe2md
Project-URL: Documentation, https://mkdocstrings.github.io/griffe2md
Project-URL: Changelog, https://mkdocstrings.github.io/griffe2md/changelog
Project-URL: Repository, https://github.com/mkdocstrings/griffe2md
Project-URL: Issues, https://github.com/mkdocstrings/griffe2md/issues
Project-URL: Discussions, https://github.com/mkdocstrings/griffe2md/discussions
Project-URL: Gitter, https://gitter.im/mkdocstrings/griffe2md
Project-URL: Funding, https://github.com/sponsors/pawamoy
Requires-Python: >=3.10
Requires-Dist: griffe>=1.14
Requires-Dist: jinja2>=3.1.2
Requires-Dist: mdformat>=0.7.16
Requires-Dist: tomli>=2.0; python_version < "3.11"
